datemangler/__init__.py
datemangler/__main__.py
datemangler-0.3.0.dist-info/LICENSE
datemangler-0.3.0.dist-info/METADATA
datemangler-0.3.0.dist-info/WHEEL
datemangler-0.3.0.dist-info/entry_points.txt
datemangler-0.3.0.dist-info/top_level.txt
datemangler-0.3.0.dist-info/RECORD
