Metadata-Version: 2.1
Name: datemangler
Version: 0.3.0
Summary: This script modifies the last four bits of an NTFS timestamp to hide information.
Author: Stephan Klein
License: Copyright (c) 2015-2024 Stephan Klein
Project-URL: Repository, https://github.com/privatwolke/datemangler
Project-URL: Issues, https://github.com/privatwolke/datemangler/issues
Keywords: NTFS,encryption,stenography,hidden,AES
Classifier: Development Status :: 4 - Beta
Classifier: Environment :: Console
Classifier: Intended Audience :: Science/Research
Classifier: License :: OSI Approved :: MIT License
Classifier: Natural Language :: English
Classifier: Operating System :: POSIX
Classifier: Programming Language :: Python :: 3
Classifier: Topic :: Utilities
Requires-Python: >=3.11
License-File: LICENSE
Requires-Dist: xattr
Requires-Dist: cryptography
